phoopy/__init__.py
phoopy/http/__init__.py
phoopy/http/annotations/__init__.py
phoopy/http/annotations/errorhandler.py
phoopy/http/annotations/route.py
phoopy/http/core/__init__.py
phoopy/http/core/application.py
phoopy/http/http_bundle/__init__.py
phoopy/http/http_bundle/http_bundle.py
phoopy/http/http_bundle/config/services.yml
phoopy/http/http_bundle/source/__init__.py
phoopy/http/http_bundle/source/command/__init__.py
phoopy/http/http_bundle/source/command/server_start_command.py
phoopy_http-1.0.6.dist-info/METADATA
phoopy_http-1.0.6.dist-info/WHEEL
phoopy_http-1.0.6.dist-info/top_level.txt
phoopy_http-1.0.6.dist-info/RECORD
